sqlite_veccie
