Metadata-Version: 2.1
Name: sqlite-veccie
Version: 0.1.2
Summary: A tiny sqlite extension implementing simple vector distance functions
License: This is free and unencumbered software released into the public domain.
Project-URL: source, https://github.com/mossblaser/veccie
License-File: LICENSE
